dbbpy_test/__init__.py
dbbpy_test/compile.py
dbbpy_test/src/bindings.cp312-win_amd64.pyd
dbbpy_test/src/bindings.cpython-311-x86_64-linux-gnu.so
dbbpy_test/src/main.cpp
dbbpy_test/src/optimizer.cpp
dbbpy_test/src/optimizer.hpp
dbbpy_test/src/option_cleaner.cpp
dbbpy_test/src/option_cleaner.hpp
dbbpy_test/src/utils.hpp
dbbpy_test-0.1.2.dist-info/METADATA
dbbpy_test-0.1.2.dist-info/WHEEL
dbbpy_test-0.1.2.dist-info/entry_points.txt
dbbpy_test-0.1.2.dist-info/RECORD
