Metadata-Version: 2.1
Name: dbbpy-test
Version: 0.1.2
Summary: 
Author: luca-donatelli
Author-email: luca.donatelli1990@gmail.com
Requires-Python: >=3.8,<4.0
Classifier: Programming Language :: Python :: 3
Classifier: Programming Language :: Python :: 3.8
Classifier: Programming Language :: Python :: 3.9
Classifier: Programming Language :: Python :: 3.10
Classifier: Programming Language :: Python :: 3.11
Classifier: Programming Language :: Python :: 3.12
Requires-Dist: numpy (>=1.21,<2.0)
Requires-Dist: pybind11 (>=2.6,<3.0)
